amsaf/__init__.py
amsaf/amsaf.py
amsaf/cli.py
amsaf-0.1.1.dist-info/DESCRIPTION.rst
amsaf-0.1.1.dist-info/METADATA
amsaf-0.1.1.dist-info/RECORD
amsaf-0.1.1.dist-info/WHEEL
amsaf-0.1.1.dist-info/entry_points.txt
amsaf-0.1.1.dist-info/metadata.json
amsaf-0.1.1.dist-info/top_level.txt
