Metadata-Version: 2.0
Name: amsaf
Version: 0.1.1
Summary: The HART Lab's tools for registration-based segmentation
Home-page: https://github.com/hart-seg-reg/amsaf
Author: Laura Hallock
Author-email: hartsegproject@gmail.com
License: MIT license
Keywords: amsaf
Platform: UNKNOWN
Classifier: Development Status :: 2 - Pre-Alpha
Classifier: Intended Audience :: Developers
Classifier: License :: OSI Approved :: MIT License
Classifier: Natural Language :: English
Classifier: Programming Language :: Python :: 2
Classifier: Programming Language :: Python :: 2.6
Classifier: Programming Language :: Python :: 2.7
Requires-Dist: Click (>=6.0)
Requires-Dist: scipy
Requires-Dist: scikit-learn
Requires-Dist: numpy
Requires-Dist: SimpleITK
